src/__init__.py
src/openstack_admin.py
src/openstack_metrics_collector.py
src/openstack_optimization.py
src/openstack_summary.py
src/openstack_toolbox.py
src/weekly_notification_optimization.py
openstack_toolbox-1.4.0.dist-info/METADATA
openstack_toolbox-1.4.0.dist-info/WHEEL
openstack_toolbox-1.4.0.dist-info/entry_points.txt
openstack_toolbox-1.4.0.dist-info/RECORD
