Metadata-Version: 2.4
Name: openstack-toolbox
Version: 1.4.0
Summary: A toolbox for OpenStack (Infomaniak hosting)
Project-URL: Homepage, https://github.com/ClaraVnk/openstack-toolbox
Project-URL: Issues, https://github.com/ClaraVnk/openstack-toolbox/issues
Author-email: Loutre <loutre@ikmail.com>
License-Expression: Apache-2.0
Classifier: License :: OSI Approved :: Apache Software License
Classifier: Operating System :: OS Independent
Classifier: Programming Language :: Python :: 3
Requires-Python: >=3.9
Requires-Dist: openstacksdk
Requires-Dist: prometheus-client
Requires-Dist: python-dotenv
Requires-Dist: python-json-logger
Requires-Dist: requests
Requires-Dist: rich
Requires-Dist: tomli
